setup.py
pygl_nf/GL.py
pygl_nf/GL_GAME_TOOLS.py
pygl_nf/GL_MATH.py
pygl_nf/GL_PREFABS.py
pygl_nf/GL_SERVER_TOOLS.py
pygl_nf/GL_TOLK.py
pygl_nf/GL_TRIGGERS.py
pygl_nf/GL_VFX.py
pygl_nf/__init__.py
pygl_nf.egg-info/PKG-INFO
pygl_nf.egg-info/SOURCES.txt
pygl_nf.egg-info/dependency_links.txt
pygl_nf.egg-info/not-zip-safe
pygl_nf.egg-info/requires.txt
pygl_nf.egg-info/top_level.txt