Metadata-Version: 2.1
Name: pygl-nf
Version: 22.1
Summary: small and compact graphick distributions
Author-email: pvana621@gmail.com
